task/__init__.py
task/database.py
task/main.py
task/task_add.py
task/task_describe.py
task/task_done.py
task/task_list.py
task/task_rm.py
task/utils.py
task-0.2.5.dist-info/entry_points.txt
task-0.2.5.dist-info/LICENSE
task-0.2.5.dist-info/WHEEL
task-0.2.5.dist-info/METADATA
task-0.2.5.dist-info/RECORD
