Metadata-Version: 2.1
Name: task
Version: 0.2.5
Summary: Task cli tool
Home-page: https://github.com/matteyeux/task
License: MIT
Keywords: task,pytask
Author: matteyeux
Requires-Python: >=3.7,<4.0
Classifier: Development Status :: 3 - Alpha
Classifier: Intended Audience :: Developers
Classifier: Intended Audience :: Education
Classifier: Intended Audience :: System Administrators
Classifier: License :: OSI Approved :: MIT License
Classifier: Programming Language :: Python :: 3
Classifier: Programming Language :: Python :: 3.7
Classifier: Programming Language :: Python :: 3.8
Classifier: Programming Language :: Python :: 3.9
Classifier: Topic :: Utilities
Requires-Dist: SQLAlchemy (>=1.3.22,<2.0.0)
Requires-Dist: click (>=7.1.2,<8.0.0)
Requires-Dist: click-aliases (>=1.0.1,<2.0.0)
Requires-Dist: click-default-group (>=1.2.2,<2.0.0)
Requires-Dist: click-help-colors (>=0.9,<0.10)
Requires-Dist: python-dateutil (>=2.8.1,<3.0.0)
Requires-Dist: rich (>=9.8.2,<10.0.0)
Requires-Dist: tabulate (>=0.8.7,<0.9.0)
Project-URL: Repository, https://github.com/matteyeux/task
